{
  "placeholderImages": [
    {
      "id": "main-logo",
      "description": "ResQMate Official Logo - A colorful heart within a shield, featuring a white medical cross and a caring hand.",
      "imageUrl": "/pp.png",
      "imageHint": "humanitarian logo"
    },
    {
      "id": "login-bg",
      "description": "The mission control background image for the login terminal.",
      "imageUrl": "/bg.png",
      "imageHint": "mission control"
    },
    {
      "id": "hero-bg",
      "description": "Humanitarian relief efforts background",
      "imageUrl": "https://picsum.photos/seed/resqhero/1200/600",
      "imageHint": "humanitarian relief"
    },
    {
      "id": "how-it-works-hero",
      "description": "Abstract visualization of emergency coordination network",
      "imageUrl": "https://picsum.photos/seed/howitworks/1200/600",
      "imageHint": "coordination network"
    },
    {
      "id": "story-1",
      "description": "Volunteers helping in a flood-affected area",
      "imageUrl": "https://picsum.photos/seed/story1/800/600",
      "imageHint": "flood relief"
    },
    {
      "id": "story-2",
      "description": "Medical professionals providing aid in a camp",
      "imageUrl": "https://picsum.photos/seed/story2/800/600",
      "imageHint": "medical camp"
    },
    {
      "id": "story-3",
      "description": "Logistics team coordinating supplies",
      "imageUrl": "https://picsum.photos/seed/story3/800/600",
      "imageHint": "relief logistics"
    }
  ]
}